zetasketch_py-0.1.3.dist-info/METADATA
zetasketch_py-0.1.3.dist-info/WHEEL
zetasketch_py.libs/libgcc_s-39080030.so.1
zetasketch_py/__init__.py
zetasketch_py/__init__.pyi
zetasketch_py/py.typed
zetasketch_py/zetasketch_py.pypy311-pp73-aarch64-linux-gnu.so
zetasketch_py-0.1.3.dist-info/RECORD
